shopcloud_organize/__init__.py
shopcloud_organize/__main__.py
shopcloud_organize/cli.py
shopcloud_organize/exceptions.py
shopcloud_organize/helpers.py
shopcloud_organize-1.7.0.data/scripts/organize
shopcloud_organize-1.7.0.dist-info/LICENSE
shopcloud_organize-1.7.0.dist-info/METADATA
shopcloud_organize-1.7.0.dist-info/WHEEL
shopcloud_organize-1.7.0.dist-info/top_level.txt
shopcloud_organize-1.7.0.dist-info/RECORD
