Metadata-Version: 2.1
Name: shopcloud_organize
Version: 1.7.0
Summary: CLI tool for task management @talk-point
Home-page: https://github.com/Talk-Point/shopcloud-organize
Author: Konstantin Stoldt
Author-email: konstantin.stoldt@talk-point.de
License: MIT
Keywords: CLI
License-File: LICENSE
Requires-Dist: pyyaml
Requires-Dist: requests
Requires-Dist: shopcloud-secrethub
Requires-Dist: tqdm
